[{"average": 12795000.0, "date": "2019-05-19", "highest": 12795000.0, "lowest": 12795000.0, "order_count": 1, "volume": 1}, {"average": 12795000.0, "date": "2019-07-30", "highest": 12795000.0, "lowest": 12795000.0, "order_count": 1, "volume": 1}, {"average": 12295000.0, "date": "2019-08-28", "highest": 12295000.0, "lowest": 12295000.0, "order_count": 1, "volume": 1}, {"average": 12295000.0, "date": "2019-09-20", "highest": 12295000.0, "lowest": 12295000.0, "order_count": 1, "volume": 1}, {"average": 12294999.99, "date": "2019-09-26", "highest": 12294999.99, "lowest": 12294999.99, "order_count": 1, "volume": 1}, {"average": 12295000.0, "date": "2019-09-27", "highest": 12295000.0, "lowest": 12295000.0, "order_count": 1, "volume": 1}]