[{"average": 56254125.0, "date": "2019-03-02", "highest": 56254125.0, "lowest": 56254125.0, "order_count": 1, "volume": 1}, {"average": 56254125.0, "date": "2019-03-13", "highest": 56254125.0, "lowest": 56254125.0, "order_count": 1, "volume": 1}, {"average": 56254125.0, "date": "2019-03-19", "highest": 56254125.0, "lowest": 56254125.0, "order_count": 1, "volume": 1}, {"average": 56289654.0, "date": "2019-05-04", "highest": 56289654.0, "lowest": 56289654.0, "order_count": 1, "volume": 1}, {"average": 56389541.0, "date": "2019-05-15", "highest": 56389541.0, "lowest": 56389541.0, "order_count": 1, "volume": 1}, {"average": 124999999.99, "date": "2019-05-31", "highest": 124999999.99, "lowest": 124999999.99, "order_count": 1, "volume": 1}, {"average": 59389541.0, "date": "2019-06-03", "highest": 59389541.0, "lowest": 59389541.0, "order_count": 1, "volume": 1}, {"average": 59389541.0, "date": "2019-06-13", "highest": 59389541.0, "lowest": 59389541.0, "order_count": 1, "volume": 1}, {"average": 79541214.0, "date": "2019-08-24", "highest": 79541214.0, "lowest": 79541214.0, "order_count": 1, "volume": 1}, {"average": 79541214.0, "date": "2019-08-26", "highest": 79541214.0, "lowest": 79541214.0, "order_count": 1, "volume": 1}, {"average": 79541214.0, "date": "2019-10-18", "highest": 79541214.0, "lowest": 79541214.0, "order_count": 1, "volume": 1}, {"average": 79124587.0, "date": "2019-10-21", "highest": 79124587.0, "lowest": 79124587.0, "order_count": 1, "volume": 1}, {"average": 79332900.5, "date": "2019-10-22", "highest": 79332900.5, "lowest": 79332900.5, "order_count": 1, "volume": 1}, {"average": 79334524.0, "date": "2019-11-01", "highest": 79334524.0, "lowest": 79334524.0, "order_count": 1, "volume": 1}, {"average": 79334524.0, "date": "2019-11-13", "highest": 79334524.0, "lowest": 79334524.0, "order_count": 1, "volume": 1}, {"average": 79334523.0, "date": "2019-11-23", "highest": 79334523.0, "lowest": 79334523.0, "order_count": 1, "volume": 1}, {"average": 79635451.0, "date": "2019-12-27", "highest": 79635451.0, "lowest": 79635451.0, "order_count": 1, "volume": 1}, {"average": 87000000.0, "date": "2019-12-30", "highest": 87000000.0, "lowest": 87000000.0, "order_count": 1, "volume": 1}, {"average": 79635421.0, "date": "2020-01-27", "highest": 79635421.0, "lowest": 79635421.0, "order_count": 1, "volume": 1}, {"average": 79635419.96, "date": "2020-02-05", "highest": 79635419.96, "lowest": 79635419.96, "order_count": 1, "volume": 1}, {"average": 79635420.0, "date": "2020-02-12", "highest": 79635420.0, "lowest": 79635420.0, "order_count": 1, "volume": 1}, {"average": 79635420.0, "date": "2020-03-08", "highest": 79635420.0, "lowest": 79635420.0, "order_count": 1, "volume": 1}, {"average": 79635420.0, "date": "2020-04-01", "highest": 79635420.0, "lowest": 79635420.0, "order_count": 1, "volume": 1}, {"average": 58890000.0, "date": "2020-04-17", "highest": 58890000.0, "lowest": 58890000.0, "order_count": 1, "volume": 1}]