[{"average": 128405880.28, "date": "2019-03-01", "highest": 128459998.88, "lowest": 128000000.0, "order_count": 10, "volume": 17}, {"average": 127703703.26, "date": "2019-03-02", "highest": 127999999.79, "lowest": 127555554.99, "order_count": 6, "volume": 6}, {"average": 126048592.98, "date": "2019-03-03", "highest": 127999123.94, "lowest": 80030008.0, "order_count": 20, "volume": 27}, {"average": 124427745.18, "date": "2019-03-04", "highest": 127998773.12, "lowest": 105000000.0, "order_count": 6, "volume": 7}, {"average": 124801127.79, "date": "2019-03-05", "highest": 127998422.07, "lowest": 80039007.78, "order_count": 12, "volume": 15}, {"average": 127998421.95, "date": "2019-03-06", "highest": 127998422.02, "lowest": 127998421.94, "order_count": 12, "volume": 20}, {"average": 127998421.0, "date": "2019-03-07", "highest": 127998421.82, "lowest": 127998420.18, "order_count": 4, "volume": 4}, {"average": 127996563.12, "date": "2019-03-08", "highest": 127997420.22, "lowest": 127996420.27, "order_count": 6, "volume": 7}, {"average": 129500205.25, "date": "2019-03-09", "highest": 163949374.0, "lowest": 127997420.22, "order_count": 17, "volume": 20}, {"average": 127998597.12, "date": "2019-03-10", "highest": 128000000.0, "lowest": 127998421.8, "order_count": 15, "volume": 18}, {"average": 127807499.39, "date": "2019-03-11", "highest": 128000000.0, "lowest": 127789999.33, "order_count": 10, "volume": 12}, {"average": 127924860.93, "date": "2019-03-12", "highest": 127998421.8, "lowest": 127789999.33, "order_count": 15, "volume": 17}, {"average": 127997253.82, "date": "2019-03-13", "highest": 127998421.79, "lowest": 127996419.74, "order_count": 11, "volume": 11}, {"average": 123637944.16, "date": "2019-03-14", "highest": 127998421.71, "lowest": 80039010.0, "order_count": 9, "volume": 11}, {"average": 127998421.7, "date": "2019-03-15", "highest": 127998421.7, "lowest": 127998421.69, "order_count": 3, "volume": 4}, {"average": 126998618.89, "date": "2019-03-16", "highest": 127998421.62, "lowest": 120000000.0, "order_count": 5, "volume": 8}, {"average": 127998351.16, "date": "2019-03-17", "highest": 127998421.59, "lowest": 127997999.0, "order_count": 10, "volume": 12}, {"average": 127998421.56, "date": "2019-03-18", "highest": 127998421.56, "lowest": 127998421.56, "order_count": 3, "volume": 3}, {"average": 127998421.42, "date": "2019-03-19", "highest": 127998421.42, "lowest": 127998421.41, "order_count": 7, "volume": 9}, {"average": 122669686.26, "date": "2019-03-20", "highest": 127998420.57, "lowest": 80039810.59, "order_count": 7, "volume": 9}, {"average": 127998420.25, "date": "2019-03-21", "highest": 127998420.28, "lowest": 127998420.22, "order_count": 3, "volume": 4}, {"average": 118039811.83, "date": "2019-03-22", "highest": 118039812.0, "lowest": 118039811.0, "order_count": 10, "volume": 11}, {"average": 115754097.63, "date": "2019-03-23", "highest": 117039811.79, "lowest": 114039812.08, "order_count": 6, "volume": 7}, {"average": 116999999.92, "date": "2019-03-24", "highest": 117039811.8, "lowest": 116960187.98, "order_count": 10, "volume": 14}, {"average": 116960188.06, "date": "2019-03-25", "highest": 116960188.07, "lowest": 116960188.0, "order_count": 6, "volume": 10}, {"average": 116994312.56, "date": "2019-03-26", "highest": 116999999.98, "lowest": 116960188.04, "order_count": 13, "volume": 14}, {"average": 116999999.96, "date": "2019-03-27", "highest": 116999999.97, "lowest": 116999999.96, "order_count": 3, "volume": 3}, {"average": 116999999.9, "date": "2019-03-28", "highest": 116999999.9, "lowest": 116999999.9, "order_count": 2, "volume": 2}, {"average": 116999559.65, "date": "2019-03-29", "highest": 116999599.9, "lowest": 116999400.0, "order_count": 7, "volume": 10}, {"average": 116999526.12, "date": "2019-03-30", "highest": 116999549.99, "lowest": 116999502.01, "order_count": 6, "volume": 8}, {"average": 115489585.78, "date": "2019-03-31", "highest": 116999550.0, "lowest": 80759919.11, "order_count": 17, "volume": 24}, {"average": 116999598.96, "date": "2019-04-01", "highest": 116999598.96, "lowest": 116999598.96, "order_count": 3, "volume": 3}, {"average": 117307322.12, "date": "2019-04-02", "highest": 120999999.99, "lowest": 116999598.96, "order_count": 9, "volume": 13}, {"average": 117332464.56, "date": "2019-04-03", "highest": 119000000.0, "lowest": 80759919.11, "order_count": 12, "volume": 16}, {"average": 116870907.97, "date": "2019-04-04", "highest": 116950081.52, "lowest": 116000000.0, "order_count": 9, "volume": 12}, {"average": 116950080.97, "date": "2019-04-05", "highest": 116950080.98, "lowest": 116950080.97, "order_count": 7, "volume": 7}, {"average": 115999999.99, "date": "2019-04-06", "highest": 115999999.99, "lowest": 115999999.99, "order_count": 7, "volume": 8}, {"average": 114524959.2, "date": "2019-04-07", "highest": 115999999.97, "lowest": 113049918.43, "order_count": 8, "volume": 8}, {"average": 112881239.8, "date": "2019-04-08", "highest": 113000000.0, "lowest": 111999999.99, "order_count": 7, "volume": 8}, {"average": 108317484.22, "date": "2019-04-09", "highest": 110999999.98, "lowest": 80759892.42, "order_count": 10, "volume": 12}, {"average": 110999999.3, "date": "2019-04-10", "highest": 110999999.98, "lowest": 110999998.96, "order_count": 9, "volume": 12}, {"average": 110999996.63, "date": "2019-04-11", "highest": 110999998.96, "lowest": 110999991.98, "order_count": 2, "volume": 3}, {"average": 110999991.0, "date": "2019-04-12", "highest": 110999991.0, "lowest": 110999991.0, "order_count": 8, "volume": 9}, {"average": 110999970.41, "date": "2019-04-13", "highest": 110999972.44, "lowest": 110999970.0, "order_count": 5, "volume": 6}, {"average": 110999919.82, "date": "2019-04-14", "highest": 110999970.0, "lowest": 110999895.0, "order_count": 11, "volume": 12}, {"average": 93291311.06, "date": "2019-04-15", "highest": 110999895.0, "lowest": 80759896.0, "order_count": 5, "volume": 7}, {"average": 106430917.67, "date": "2019-04-16", "highest": 107999793.13, "lowest": 80759895.0, "order_count": 18, "volume": 18}, {"average": 106998659.8, "date": "2019-04-17", "highest": 107997389.22, "lowest": 104999998.95, "order_count": 5, "volume": 6}, {"average": 95624693.35, "date": "2019-04-18", "highest": 104899999.99, "lowest": 67879947.01, "order_count": 16, "volume": 17}, {"average": 103999999.99, "date": "2019-04-19", "highest": 103999999.99, "lowest": 102999999.99, "order_count": 4, "volume": 5}, {"average": 102698999.98, "date": "2019-04-20", "highest": 102999999.97, "lowest": 99990000.0, "order_count": 8, "volume": 10}, {"average": 99641666.66, "date": "2019-04-21", "highest": 103900000.0, "lowest": 55000000.0, "order_count": 11, "volume": 12}, {"average": 107996262.87, "date": "2019-04-22", "highest": 107997388.99, "lowest": 107995386.99, "order_count": 7, "volume": 8}, {"average": 107989052.98, "date": "2019-04-23", "highest": 107992386.77, "lowest": 107982385.41, "order_count": 3, "volume": 3}, {"average": 107982378.58, "date": "2019-04-24", "highest": 107982378.58, "lowest": 107982378.58, "order_count": 1, "volume": 1}, {"average": 107583900.7, "date": "2019-04-25", "highest": 107982378.58, "lowest": 105989989.0, "order_count": 8, "volume": 10}, {"average": 105716475.98, "date": "2019-04-26", "highest": 107382379.43, "lowest": 103000000.0, "order_count": 5, "volume": 5}, {"average": 106070513.76, "date": "2019-04-27", "highest": 106993694.79, "lowest": 105865097.19, "order_count": 12, "volume": 12}, {"average": 105895346.72, "date": "2019-04-28", "highest": 105900099.54, "lowest": 105865097.0, "order_count": 9, "volume": 10}, {"average": 99883439.33, "date": "2019-04-29", "highest": 106950343.47, "lowest": 67500000.0, "order_count": 10, "volume": 12}, {"average": 97285706.94, "date": "2019-04-30", "highest": 104499977.31, "lowest": 55000000.0, "order_count": 6, "volume": 7}, {"average": 105442627.08, "date": "2019-05-01", "highest": 107901999.0, "lowest": 101999999.99, "order_count": 11, "volume": 12}, {"average": 100126252.08, "date": "2019-05-02", "highest": 107801998.33, "lowest": 55000004.77, "order_count": 8, "volume": 8}, {"average": 105567667.73, "date": "2019-05-03", "highest": 107801995.0, "lowest": 103000010.41, "order_count": 6, "volume": 6}, {"average": 103537749.33, "date": "2019-05-04", "highest": 104000000.0, "lowest": 100000000.0, "order_count": 7, "volume": 8}, {"average": 98102768.52, "date": "2019-05-05", "highest": 103999887.99, "lowest": 68021981.89, "order_count": 17, "volume": 20}, {"average": 109475831.15, "date": "2019-05-06", "highest": 127998480.26, "lowest": 103999887.99, "order_count": 20, "volume": 39}, {"average": 121149084.08, "date": "2019-05-07", "highest": 127998538.68, "lowest": 108023986.26, "order_count": 6, "volume": 7}, {"average": 127998528.96, "date": "2019-05-08", "highest": 127998531.5, "lowest": 127998525.3, "order_count": 9, "volume": 12}, {"average": 119414854.89, "date": "2019-05-09", "highest": 127979999.0, "lowest": 68023990.22, "order_count": 7, "volume": 7}, {"average": 124431572.14, "date": "2019-05-10", "highest": 127961459.32, "lowest": 115000000.0, "order_count": 8, "volume": 11}, {"average": 127979998.7, "date": "2019-05-11", "highest": 127979998.99, "lowest": 127979998.0, "order_count": 7, "volume": 7}, {"average": 125315725.96, "date": "2019-05-12", "highest": 126989988.99, "lowest": 112007999.37, "order_count": 14, "volume": 15}, {"average": 127261298.34, "date": "2019-05-13", "highest": 127998538.69, "lowest": 126966010.97, "order_count": 6, "volume": 7}, {"average": 126964999.83, "date": "2019-05-14", "highest": 126965989.0, "lowest": 126964010.98, "order_count": 6, "volume": 6}, {"average": 119149451.85, "date": "2019-05-15", "highest": 126964010.96, "lowest": 68206796.39, "order_count": 8, "volume": 8}, {"average": 125992099.4, "date": "2019-05-16", "highest": 126961989.04, "lowest": 119206817.06, "order_count": 8, "volume": 8}, {"average": 122989062.29, "date": "2019-05-17", "highest": 126960011.0, "lowest": 115000000.0, "order_count": 9, "volume": 14}, {"average": 126462846.92, "date": "2019-05-18", "highest": 126959988.99, "lowest": 120000000.0, "order_count": 11, "volume": 14}, {"average": 120335817.02, "date": "2019-05-19", "highest": 126959987.99, "lowest": 68386817.95, "order_count": 9, "volume": 11}, {"average": 123386788.08, "date": "2019-05-20", "highest": 123386792.35, "lowest": 123386783.88, "order_count": 5, "volume": 6}, {"average": 123386783.54, "date": "2019-05-21", "highest": 123386783.6, "lowest": 123386783.42, "order_count": 2, "volume": 3}, {"average": 123386781.62, "date": "2019-05-22", "highest": 123386783.0, "lowest": 123386780.97, "order_count": 13, "volume": 14}, {"average": 123386780.96, "date": "2019-05-23", "highest": 123386780.97, "lowest": 123386780.96, "order_count": 7, "volume": 7}, {"average": 123048101.01, "date": "2019-05-24", "highest": 123386778.95, "lowest": 119999999.99, "order_count": 8, "volume": 10}, {"average": 120420846.08, "date": "2019-05-25", "highest": 123386777.98, "lowest": 70000013.35, "order_count": 14, "volume": 18}, {"average": 123318236.86, "date": "2019-05-26", "highest": 123386776.99, "lowest": 123213223.01, "order_count": 13, "volume": 15}, {"average": 117767118.03, "date": "2019-05-27", "highest": 123386776.97, "lowest": 70000018.51, "order_count": 18, "volume": 19}, {"average": 123126253.46, "date": "2019-05-28", "highest": 123386774.95, "lowest": 120000000.0, "order_count": 11, "volume": 13}, {"average": 123019577.17, "date": "2019-05-29", "highest": 123386773.04, "lowest": 120999999.87, "order_count": 12, "volume": 13}, {"average": 120999999.46, "date": "2019-05-30", "highest": 120999999.46, "lowest": 120999999.46, "order_count": 6, "volume": 7}, {"average": 114267414.64, "date": "2019-05-31", "highest": 120999999.44, "lowest": 90004992.92, "order_count": 8, "volume": 9}, {"average": 121270033.96, "date": "2019-06-01", "highest": 123386757.91, "lowest": 119999999.99, "order_count": 6, "volume": 8}, {"average": 119999999.99, "date": "2019-06-02", "highest": 119999999.99, "lowest": 119999999.99, "order_count": 11, "volume": 15}, {"average": 118615384.61, "date": "2019-06-03", "highest": 119999999.99, "lowest": 115000000.0, "order_count": 11, "volume": 13}, {"average": 119674870.47, "date": "2019-06-04", "highest": 123386757.0, "lowest": 118999999.98, "order_count": 9, "volume": 13}, {"average": 118999950.44, "date": "2019-06-05", "highest": 118999950.54, "lowest": 118999950.32, "order_count": 7, "volume": 8}, {"average": 118999950.08, "date": "2019-06-06", "highest": 118999950.33, "lowest": 118999949.68, "order_count": 8, "volume": 9}, {"average": 116916620.18, "date": "2019-06-07", "highest": 118999949.63, "lowest": 94000000.99, "order_count": 9, "volume": 12}, {"average": 115235250.38, "date": "2019-06-08", "highest": 118999947.5, "lowest": 94000001.01, "order_count": 13, "volume": 17}, {"average": 118319952.34, "date": "2019-06-09", "highest": 118979942.03, "lowest": 115000000.0, "order_count": 4, "volume": 6}, {"average": 118979932.03, "date": "2019-06-10", "highest": 118979940.71, "lowest": 118979924.85, "order_count": 10, "volume": 10}, {"average": 118979924.52, "date": "2019-06-11", "highest": 118979924.87, "lowest": 118979924.17, "order_count": 2, "volume": 2}, {"average": 117154566.54, "date": "2019-06-12", "highest": 118979924.13, "lowest": 114544599.91, "order_count": 12, "volume": 17}, {"average": 105984114.5, "date": "2019-06-13", "highest": 114544590.82, "lowest": 94000002.0, "order_count": 10, "volume": 10}, {"average": 114544514.2, "date": "2019-06-14", "highest": 114544576.0, "lowest": 114544419.0, "order_count": 6, "volume": 10}, {"average": 114544371.39, "date": "2019-06-15", "highest": 114544417.93, "lowest": 114544090.0, "order_count": 16, "volume": 21}, {"average": 114544005.17, "date": "2019-06-16", "highest": 114544089.97, "lowest": 114543968.0, "order_count": 12, "volume": 17}, {"average": 114543947.97, "date": "2019-06-17", "highest": 114543947.97, "lowest": 114543947.96, "order_count": 4, "volume": 6}, {"average": 109077696.62, "date": "2019-06-18", "highest": 109999998.94, "lowest": 99000000.0, "order_count": 7, "volume": 7}, {"average": 110378653.9, "date": "2019-06-19", "highest": 114543861.0, "lowest": 109999998.71, "order_count": 9, "volume": 12}, {"average": 109999998.64, "date": "2019-06-20", "highest": 109999998.68, "lowest": 109999998.52, "order_count": 8, "volume": 8}, {"average": 109999998.4, "date": "2019-06-21", "highest": 109999998.52, "lowest": 109999998.26, "order_count": 7, "volume": 9}, {"average": 98110581.23, "date": "2019-06-22", "highest": 109999880.0, "lowest": 70039001.25, "order_count": 9, "volume": 11}, {"average": 103469054.69, "date": "2019-06-23", "highest": 109999868.8, "lowest": 100039999.0, "order_count": 9, "volume": 11}, {"average": 105264760.89, "date": "2019-06-24", "highest": 107999999.0, "lowest": 70040000.0, "order_count": 10, "volume": 14}, {"average": 108672498.09, "date": "2019-06-25", "highest": 199999999.0, "lowest": 107999994.65, "order_count": 12, "volume": 12}, {"average": 107999994.62, "date": "2019-06-26", "highest": 107999994.65, "lowest": 107999994.6, "order_count": 7, "volume": 12}, {"average": 107999994.61, "date": "2019-06-27", "highest": 107999994.62, "lowest": 107999994.6, "order_count": 11, "volume": 13}, {"average": 105591599.13, "date": "2019-06-28", "highest": 109999867.61, "lowest": 87550000.0, "order_count": 11, "volume": 12}, {"average": 109999989.86, "date": "2019-06-29", "highest": 109999989.98, "lowest": 109999989.84, "order_count": 13, "volume": 15}, {"average": 109023623.7, "date": "2019-06-30", "highest": 112271429.34, "lowest": 70050000.0, "order_count": 11, "volume": 13}, {"average": 115678142.82, "date": "2019-07-01", "highest": 126978989.0, "lowest": 114550000.0, "order_count": 9, "volume": 11}, {"average": 114246666.66, "date": "2019-07-02", "highest": 114550000.0, "lowest": 110000000.0, "order_count": 9, "volume": 15}, {"average": 114550000.0, "date": "2019-07-03", "highest": 114550000.0, "lowest": 114550000.0, "order_count": 7, "volume": 8}, {"average": 108803831.14, "date": "2019-07-04", "highest": 114550000.0, "lowest": 70040000.0, "order_count": 7, "volume": 14}, {"average": 161369873.49, "date": "2019-07-05", "highest": 183999999.99, "lowest": 138989999.49, "order_count": 7, "volume": 8}, {"average": 129873572.11, "date": "2019-07-06", "highest": 149999998.92, "lowest": 70100000.0, "order_count": 12, "volume": 14}, {"average": 144999999.74, "date": "2019-07-07", "highest": 144999999.91, "lowest": 144999999.57, "order_count": 6, "volume": 6}, {"average": 143833333.21, "date": "2019-07-08", "highest": 144999999.65, "lowest": 142999999.97, "order_count": 5, "volume": 6}, {"average": 134225413.04, "date": "2019-07-09", "highest": 141999980.0, "lowest": 129063562.57, "order_count": 4, "volume": 5}, {"average": 127999985.31, "date": "2019-07-10", "highest": 127999987.96, "lowest": 127999980.0, "order_count": 3, "volume": 3}, {"average": 119378725.0, "date": "2019-07-11", "highest": 126999956.62, "lowest": 70030015.0, "order_count": 7, "volume": 8}, {"average": 123093124.57, "date": "2019-07-12", "highest": 126800024.56, "lowest": 120000000.0, "order_count": 10, "volume": 15}, {"average": 125169999.24, "date": "2019-07-13", "highest": 126799994.99, "lowest": 112130004.86, "order_count": 8, "volume": 9}, {"average": 126692293.72, "date": "2019-07-14", "highest": 126799989.92, "lowest": 126599979.98, "order_count": 10, "volume": 13}, {"average": 122117988.42, "date": "2019-07-15", "highest": 125699988.83, "lowest": 115000000.0, "order_count": 11, "volume": 14}, {"average": 124987489.07, "date": "2019-07-16", "highest": 125699987.96, "lowest": 120000000.0, "order_count": 8, "volume": 8}, {"average": 118102839.79, "date": "2019-07-17", "highest": 125389989.96, "lowest": 105000000.0, "order_count": 6, "volume": 14}, {"average": 125387859.55, "date": "2019-07-18", "highest": 125389807.1, "lowest": 125386880.0, "order_count": 9, "volume": 12}, {"average": 120493943.62, "date": "2019-07-19", "highest": 125389799.99, "lowest": 115000000.0, "order_count": 11, "volume": 11}, {"average": 126841654.66, "date": "2019-07-20", "highest": 179999999.0, "lowest": 125386979.94, "order_count": 9, "volume": 12}, {"average": 114830568.6, "date": "2019-07-21", "highest": 125386949.0, "lowest": 98996000.02, "order_count": 7, "volume": 10}, {"average": 125372917.27, "date": "2019-07-22", "highest": 125386862.98, "lowest": 125366930.0, "order_count": 7, "volume": 10}, {"average": 125355986.71, "date": "2019-07-23", "highest": 125366927.89, "lowest": 125346869.07, "order_count": 7, "volume": 11}, {"average": 123299999.77, "date": "2019-07-24", "highest": 123299999.77, "lowest": 123299999.77, "order_count": 1, "volume": 1}, {"average": 117031559.69, "date": "2019-07-25", "highest": 119996009.34, "lowest": 112500000.0, "order_count": 6, "volume": 9}, {"average": 119993605.56, "date": "2019-07-26", "highest": 119996009.29, "lowest": 119989999.97, "order_count": 2, "volume": 5}, {"average": 118983296.11, "date": "2019-07-27", "highest": 118994999.98, "lowest": 118794997.96, "order_count": 13, "volume": 17}, {"average": 118628333.05, "date": "2019-07-28", "highest": 118786383.97, "lowest": 117996129.39, "order_count": 5, "volume": 5}, {"average": 116087784.44, "date": "2019-07-29", "highest": 117996110.0, "lowest": 107396069.38, "order_count": 10, "volume": 12}, {"average": 115796009.35, "date": "2019-07-30", "highest": 115796009.35, "lowest": 115796009.35, "order_count": 2, "volume": 2}, {"average": 116685018.35, "date": "2019-07-31", "highest": 116696129.46, "lowest": 116596129.4, "order_count": 6, "volume": 9}, {"average": 108371129.43, "date": "2019-08-01", "highest": 108996129.48, "lowest": 98996129.48, "order_count": 4, "volume": 4}, {"average": 109688745.83, "date": "2019-08-02", "highest": 116420286.69, "lowest": 108996129.48, "order_count": 7, "volume": 7}, {"average": 112954768.7, "date": "2019-08-03", "highest": 116444423.5, "lowest": 98996129.5, "order_count": 5, "volume": 5}, {"average": 116380397.97, "date": "2019-08-04", "highest": 116444442.84, "lowest": 115996129.5, "order_count": 7, "volume": 7}, {"average": 115577776.8, "date": "2019-08-05", "highest": 116444442.0, "lowest": 115000000.0, "order_count": 5, "volume": 5}, {"average": 116671837.91, "date": "2019-08-06", "highest": 118994998.99, "lowest": 116444442.87, "order_count": 10, "volume": 13}, {"average": 116772902.36, "date": "2019-08-07", "highest": 118994998.98, "lowest": 98996129.49, "order_count": 8, "volume": 9}, {"average": 117688162.81, "date": "2019-08-08", "highest": 118994998.64, "lowest": 115000000.0, "order_count": 10, "volume": 13}, {"average": 118994998.59, "date": "2019-08-09", "highest": 118994998.64, "lowest": 118994998.53, "order_count": 4, "volume": 5}, {"average": 113597999.16, "date": "2019-08-10", "highest": 118994997.9, "lowest": 109999999.99, "order_count": 5, "volume": 5}, {"average": 104777377.15, "date": "2019-08-11", "highest": 115823594.89, "lowest": 98996129.49, "order_count": 9, "volume": 12}, {"average": 112952950.02, "date": "2019-08-12", "highest": 115823589.96, "lowest": 100000000.0, "order_count": 5, "volume": 6}, {"average": 114137476.3, "date": "2019-08-13", "highest": 115823584.99, "lowest": 109000000.0, "order_count": 5, "volume": 5}, {"average": 112658868.0, "date": "2019-08-14", "highest": 115823585.0, "lowest": 99999999.99, "order_count": 5, "volume": 5}, {"average": 99600000.0, "date": "2019-08-15", "highest": 100000000.0, "lowest": 99000000.0, "order_count": 5, "volume": 5}, {"average": 100000000.0, "date": "2019-08-16", "highest": 100000000.0, "lowest": 99999999.99, "order_count": 4, "volume": 4}, {"average": 105187499.99, "date": "2019-08-17", "highest": 105699999.99, "lowest": 104999999.99, "order_count": 8, "volume": 8}, {"average": 101249998.49, "date": "2019-08-18", "highest": 104999999.0, "lowest": 99999999.99, "order_count": 6, "volume": 8}, {"average": 100000000.0, "date": "2019-08-19", "highest": 100000000.0, "lowest": 100000000.0, "order_count": 1, "volume": 2}, {"average": 104666659.96, "date": "2019-08-20", "highest": 104999989.95, "lowest": 103999999.97, "order_count": 3, "volume": 3}, {"average": 103553310.32, "date": "2019-08-21", "highest": 103999999.0, "lowest": 99999798.0, "order_count": 7, "volume": 9}, {"average": 99399979.9, "date": "2019-08-22", "highest": 103999994.97, "lowest": 60000000.1, "order_count": 9, "volume": 11}, {"average": 90466666.68, "date": "2019-08-23", "highest": 105699999.97, "lowest": 60000000.1, "order_count": 3, "volume": 3}, {"average": 103000000.0, "date": "2019-08-24", "highest": 103000000.0, "lowest": 103000000.0, "order_count": 2, "volume": 2}, {"average": 102000000.0, "date": "2019-08-25", "highest": 103000000.0, "lowest": 101999999.99, "order_count": 6, "volume": 6}, {"average": 102250000.07, "date": "2019-08-26", "highest": 103000000.1, "lowest": 100000000.0, "order_count": 4, "volume": 4}, {"average": 101911106.0, "date": "2019-08-27", "highest": 107699993.99, "lowest": 60000000.12, "order_count": 8, "volume": 9}, {"average": 109699988.92, "date": "2019-08-28", "highest": 109699988.92, "lowest": 109699988.92, "order_count": 4, "volume": 4}, {"average": 105181807.78, "date": "2019-08-29", "highest": 109699988.66, "lowest": 60000000.11, "order_count": 10, "volume": 11}, {"average": 109579995.56, "date": "2019-08-30", "highest": 109699988.94, "lowest": 109499999.98, "order_count": 4, "volume": 5}, {"average": 108709990.9, "date": "2019-08-31", "highest": 109699988.57, "lowest": 99999999.0, "order_count": 9, "volume": 10}, {"average": 109699988.88, "date": "2019-09-01", "highest": 109699988.94, "lowest": 109699988.57, "order_count": 6, "volume": 6}, {"average": 110826989.31, "date": "2019-09-02", "highest": 118994999.0, "lowest": 109699988.94, "order_count": 7, "volume": 7}, {"average": 109699988.94, "date": "2019-09-04", "highest": 109699988.94, "lowest": 109699988.93, "order_count": 2, "volume": 2}, {"average": 109699988.81, "date": "2019-09-05", "highest": 109699988.94, "lowest": 109699988.0, "order_count": 6, "volume": 7}, {"average": 104999368.0, "date": "2019-09-07", "highest": 104999368.0, "lowest": 104999368.0, "order_count": 2, "volume": 2}, {"average": 98179253.67, "date": "2019-09-08", "highest": 109699988.94, "lowest": 60000000.14, "order_count": 8, "volume": 9}, {"average": 118913925.45, "date": "2019-09-09", "highest": 118913925.45, "lowest": 118913925.45, "order_count": 2, "volume": 3}, {"average": 95637976.37, "date": "2019-09-10", "highest": 113456960.0, "lowest": 60000009.1, "order_count": 3, "volume": 3}, {"average": 107071428.41, "date": "2019-09-11", "highest": 107899999.8, "lowest": 104999999.95, "order_count": 4, "volume": 7}, {"average": 107339999.92, "date": "2019-09-12", "highest": 107899999.9, "lowest": 105000000.0, "order_count": 5, "volume": 5}, {"average": 102489079.67, "date": "2019-09-13", "highest": 117989980.0, "lowest": 100000017.83, "order_count": 4, "volume": 6}, {"average": 118863235.8, "date": "2019-09-14", "highest": 118994999.0, "lowest": 117989980.0, "order_count": 13, "volume": 14}, {"average": 124120428.82, "date": "2019-09-15", "highest": 125345932.0, "lowest": 123299999.94, "order_count": 11, "volume": 17}, {"average": 124638137.2, "date": "2019-09-16", "highest": 129063562.0, "lowest": 118000000.0, "order_count": 4, "volume": 5}, {"average": 117725000.0, "date": "2019-09-17", "highest": 118000000.0, "lowest": 111799999.99, "order_count": 6, "volume": 8}, {"average": 129063463.5, "date": "2019-09-18", "highest": 129063476.99, "lowest": 129063440.0, "order_count": 5, "volume": 6}, {"average": 121500000.0, "date": "2019-09-19", "highest": 125000000.0, "lowest": 117999999.99, "order_count": 2, "volume": 2}, {"average": 124547527.5, "date": "2019-09-20", "highest": 129063370.0, "lowest": 111000000.0, "order_count": 4, "volume": 4}, {"average": 108515857.01, "date": "2019-09-21", "highest": 110000052.47, "lowest": 60000053.17, "order_count": 7, "volume": 8}, {"average": 136088682.48, "date": "2019-09-22", "highest": 179999996.29, "lowest": 129063349.0, "order_count": 14, "volume": 22}, {"average": 187218266.28, "date": "2019-09-23", "highest": 199999999.0, "lowest": 148873072.64, "order_count": 8, "volume": 8}, {"average": 174558187.34, "date": "2019-09-24", "highest": 179702720.88, "lowest": 118000000.0, "order_count": 12, "volume": 12}, {"average": 179599571.99, "date": "2019-09-25", "highest": 179599980.0, "lowest": 179390612.9, "order_count": 5, "volume": 10}, {"average": 151483977.34, "date": "2019-09-26", "highest": 179290612.88, "lowest": 118000000.0, "order_count": 6, "volume": 8}, {"average": 154999994.99, "date": "2019-09-27", "highest": 159999989.98, "lowest": 150000000.0, "order_count": 4, "volume": 4}, {"average": 159800008.16, "date": "2019-09-28", "highest": 159999999.0, "lowest": 150000000.0, "order_count": 4, "volume": 5}, {"average": 162683138.15, "date": "2019-09-29", "highest": 164053570.4, "lowest": 161997920.0, "order_count": 6, "volume": 6}, {"average": 138245718.7, "date": "2019-09-30", "highest": 160290000.0, "lowest": 60000052.83, "order_count": 7, "volume": 9}, {"average": 158030163.39, "date": "2019-10-01", "highest": 159177495.28, "lowest": 149999999.99, "order_count": 8, "volume": 8}, {"average": 145712857.14, "date": "2019-10-02", "highest": 149999999.99, "lowest": 135000000.0, "order_count": 7, "volume": 7}, {"average": 132568916.82, "date": "2019-10-03", "highest": 148838489.65, "lowest": 120000000.0, "order_count": 9, "volume": 9}, {"average": 147962778.15, "date": "2019-10-04", "highest": 147962779.69, "lowest": 147962769.79, "order_count": 6, "volume": 6}, {"average": 147771912.57, "date": "2019-10-05", "highest": 147962769.79, "lowest": 147731705.78, "order_count": 6, "volume": 7}, {"average": 138719371.0, "date": "2019-10-06", "highest": 147522870.0, "lowest": 98500052.83, "order_count": 14, "volume": 16}, {"average": 146799999.99, "date": "2019-10-07", "highest": 146799999.99, "lowest": 146799999.99, "order_count": 1, "volume": 1}, {"average": 145857133.98, "date": "2019-10-08", "highest": 145999989.96, "lowest": 145000000.0, "order_count": 7, "volume": 7}, {"average": 145999971.44, "date": "2019-10-09", "highest": 145999973.27, "lowest": 145999967.79, "order_count": 3, "volume": 3}, {"average": 143333332.99, "date": "2019-10-10", "highest": 144999999.99, "lowest": 139999999.0, "order_count": 3, "volume": 3}, {"average": 144999972.18, "date": "2019-10-11", "highest": 144999984.35, "lowest": 144999960.0, "order_count": 4, "volume": 4}, {"average": 122930335.53, "date": "2019-10-12", "highest": 144826803.34, "lowest": 90000026.42, "order_count": 4, "volume": 5}, {"average": 132664736.19, "date": "2019-10-13", "highest": 144826576.65, "lowest": 129000000.0, "order_count": 6, "volume": 7}, {"average": 144819661.53, "date": "2019-10-14", "highest": 144819688.98, "lowest": 144819507.74, "order_count": 5, "volume": 8}, {"average": 145064945.03, "date": "2019-10-15", "highest": 146800000.0, "lowest": 144817702.06, "order_count": 8, "volume": 8}, {"average": 144811424.44, "date": "2019-10-16", "highest": 144813339.97, "lowest": 144808551.09, "order_count": 9, "volume": 10}, {"average": 144803748.92, "date": "2019-10-17", "highest": 144803759.99, "lowest": 144803737.84, "order_count": 2, "volume": 2}, {"average": 143490245.73, "date": "2019-10-18", "highest": 143994295.0, "lowest": 140000000.0, "order_count": 6, "volume": 8}, {"average": 135840710.35, "date": "2019-10-19", "highest": 143956200.04, "lowest": 60000052.83, "order_count": 11, "volume": 14}, {"average": 112000000.0, "date": "2019-10-20", "highest": 112000000.0, "lowest": 112000000.0, "order_count": 1, "volume": 1}, {"average": 117553460.33, "date": "2019-10-21", "highest": 129000020.0, "lowest": 60320704.0, "order_count": 5, "volume": 6}, {"average": 127144768.9, "date": "2019-10-22", "highest": 136148119.42, "lowest": 120000000.0, "order_count": 9, "volume": 11}, {"average": 143294305.6, "date": "2019-10-23", "highest": 143296230.0, "lowest": 143285638.81, "order_count": 6, "volume": 11}, {"average": 143080929.53, "date": "2019-10-24", "highest": 143285638.8, "lowest": 142876999.0, "order_count": 5, "volume": 6}, {"average": 126316666.64, "date": "2019-10-25", "highest": 127974999.96, "lowest": 123000000.0, "order_count": 4, "volume": 6}, {"average": 127974999.94, "date": "2019-10-26", "highest": 127974999.94, "lowest": 127974999.92, "order_count": 10, "volume": 14}, {"average": 118017207.31, "date": "2019-10-27", "highest": 126999999.83, "lowest": 62170452.0, "order_count": 6, "volume": 7}, {"average": 126999999.63, "date": "2019-10-28", "highest": 126999999.63, "lowest": 126999999.63, "order_count": 5, "volume": 6}, {"average": 117999999.15, "date": "2019-10-29", "highest": 126999996.62, "lowest": 115000000.0, "order_count": 4, "volume": 4}, {"average": 121112498.71, "date": "2019-10-30", "highest": 126999996.59, "lowest": 116974999.96, "order_count": 7, "volume": 8}, {"average": 117583333.18, "date": "2019-10-31", "highest": 121974999.49, "lowest": 116974999.96, "order_count": 10, "volume": 15}, {"average": 121974998.54, "date": "2019-11-01", "highest": 121974998.95, "lowest": 121974998.0, "order_count": 7, "volume": 7}, {"average": 124171773.02, "date": "2019-11-02", "highest": 127974998.99, "lowest": 121974998.88, "order_count": 19, "volume": 31}, {"average": 127974998.99, "date": "2019-11-03", "highest": 127974998.99, "lowest": 127974998.99, "order_count": 2, "volume": 2}, {"average": 89047333.98, "date": "2019-11-04", "highest": 115932166.95, "lowest": 62160001.01, "order_count": 6, "volume": 8}, {"average": 116684589.91, "date": "2019-11-05", "highest": 117420983.45, "lowest": 114160000.17, "order_count": 5, "volume": 5}, {"average": 115949999.98, "date": "2019-11-06", "highest": 116899999.96, "lowest": 115000000.0, "order_count": 2, "volume": 2}, {"average": 113453784.51, "date": "2019-11-07", "highest": 113717945.4, "lowest": 112999999.0, "order_count": 5, "volume": 5}, {"average": 113616164.81, "date": "2019-11-08", "highest": 113716918.4, "lowest": 112000000.0, "order_count": 12, "volume": 17}, {"average": 113716918.35, "date": "2019-11-09", "highest": 113716918.36, "lowest": 113716918.34, "order_count": 2, "volume": 2}, {"average": 113716898.69, "date": "2019-11-10", "highest": 113716918.38, "lowest": 113716682.17, "order_count": 11, "volume": 12}, {"average": 124606093.19, "date": "2019-11-11", "highest": 135422567.5, "lowest": 113804261.68, "order_count": 7, "volume": 8}, {"average": 142869773.19, "date": "2019-11-12", "highest": 142869785.99, "lowest": 142869714.75, "order_count": 9, "volume": 13}, {"average": 142869481.96, "date": "2019-11-13", "highest": 142869714.75, "lowest": 142869249.17, "order_count": 2, "volume": 2}, {"average": 133249992.25, "date": "2019-11-14", "highest": 133999990.0, "lowest": 129999999.0, "order_count": 4, "volume": 4}, {"average": 130777768.89, "date": "2019-11-15", "highest": 165000000.0, "lowest": 126499990.0, "order_count": 8, "volume": 9}, {"average": 123741892.13, "date": "2019-11-16", "highest": 124999990.0, "lowest": 109160895.43, "order_count": 9, "volume": 11}, {"average": 124499993.17, "date": "2019-11-17", "highest": 124999990.0, "lowest": 123999990.0, "order_count": 6, "volume": 6}, {"average": 123999989.97, "date": "2019-11-18", "highest": 123999989.99, "lowest": 123999989.96, "order_count": 4, "volume": 4}, {"average": 118391193.0, "date": "2019-11-19", "highest": 119999990.0, "lowest": 115977997.5, "order_count": 5, "volume": 5}, {"average": 119999991.8, "date": "2019-11-20", "highest": 119999999.0, "lowest": 119999990.0, "order_count": 5, "volume": 5}, {"average": 128682993.07, "date": "2019-11-21", "highest": 139161322.2, "lowest": 123980000.0, "order_count": 8, "volume": 8}, {"average": 113494655.52, "date": "2019-11-22", "highest": 139161322.18, "lowest": 62161322.21, "order_count": 3, "volume": 3}, {"average": 126661322.67, "date": "2019-11-23", "highest": 138161304.0, "lowest": 62161400.0, "order_count": 10, "volume": 14}, {"average": 138161300.98, "date": "2019-11-24", "highest": 138161307.0, "lowest": 138161299.78, "order_count": 10, "volume": 12}, {"average": 112089197.18, "date": "2019-11-25", "highest": 119999999.99, "lowest": 62161635.22, "order_count": 7, "volume": 8}, {"average": 128747432.07, "date": "2019-11-26", "highest": 137161635.2, "lowest": 120000000.0, "order_count": 6, "volume": 6}, {"average": 123813696.71, "date": "2019-11-27", "highest": 137161635.2, "lowest": 120000000.0, "order_count": 8, "volume": 9}, {"average": 119500000.0, "date": "2019-11-28", "highest": 120000000.0, "lowest": 119000000.0, "order_count": 3, "volume": 4}, {"average": 109129095.6, "date": "2019-11-29", "highest": 115000000.0, "lowest": 62161863.43, "order_count": 7, "volume": 9}, {"average": 124615291.75, "date": "2019-11-30", "highest": 129999798.78, "lowest": 120000000.0, "order_count": 9, "volume": 13}, {"average": 130332072.29, "date": "2019-12-01", "highest": 137159990.0, "lowest": 129999597.57, "order_count": 11, "volume": 13}, {"average": 127430118.85, "date": "2019-12-02", "highest": 129999900.0, "lowest": 124999999.0, "order_count": 9, "volume": 12}, {"average": 127857069.59, "date": "2019-12-03", "highest": 129999897.99, "lowest": 122499999.0, "order_count": 6, "volume": 7}, {"average": 112598014.49, "date": "2019-12-04", "highest": 124997459.06, "lowest": 63000236.21, "order_count": 5, "volume": 5}, {"average": 124992387.82, "date": "2019-12-05", "highest": 124997100.2, "lowest": 124989246.24, "order_count": 4, "volume": 5}, {"average": 137159330.11, "date": "2019-12-06", "highest": 137159576.85, "lowest": 137157944.95, "order_count": 6, "volume": 6}, {"average": 137121664.18, "date": "2019-12-07", "highest": 137156004.57, "lowest": 136879583.48, "order_count": 6, "volume": 8}, {"average": 135636401.23, "date": "2019-12-08", "highest": 137155899.98, "lowest": 125000000.0, "order_count": 7, "volume": 8}, {"average": 137000000.0, "date": "2019-12-09", "highest": 137000000.0, "lowest": 136999999.99, "order_count": 3, "volume": 4}, {"average": 112362750.47, "date": "2019-12-10", "highest": 136999999.99, "lowest": 63088251.43, "order_count": 3, "volume": 3}, {"average": 135999494.5, "date": "2019-12-11", "highest": 136998990.0, "lowest": 134999999.0, "order_count": 2, "volume": 2}, {"average": 136998990.0, "date": "2019-12-12", "highest": 136998990.0, "lowest": 136998990.0, "order_count": 2, "volume": 2}, {"average": 136997958.05, "date": "2019-12-13", "highest": 136998461.57, "lowest": 136997850.0, "order_count": 7, "volume": 10}, {"average": 136997643.07, "date": "2019-12-14", "highest": 136997702.74, "lowest": 136997515.79, "order_count": 3, "volume": 4}, {"average": 123216413.72, "date": "2019-12-15", "highest": 136996699.99, "lowest": 63205023.41, "order_count": 7, "volume": 11}, {"average": 126897367.13, "date": "2019-12-16", "highest": 135995989.93, "lowest": 63207007.51, "order_count": 6, "volume": 8}, {"average": 135497994.87, "date": "2019-12-17", "highest": 135995989.94, "lowest": 134999999.79, "order_count": 4, "volume": 4}, {"average": 133666666.52, "date": "2019-12-18", "highest": 134999999.79, "lowest": 130999999.99, "order_count": 3, "volume": 3}, {"average": 129399995.8, "date": "2019-12-19", "highest": 130000000.0, "lowest": 127999990.0, "order_count": 4, "volume": 5}, {"average": 100284456.09, "date": "2019-12-20", "highest": 124999774.79, "lowest": 63211478.13, "order_count": 4, "volume": 5}, {"average": 124016060.11, "date": "2019-12-21", "highest": 124999774.63, "lowest": 118605630.46, "order_count": 11, "volume": 13}, {"average": 124999774.51, "date": "2019-12-22", "highest": 124999774.51, "lowest": 124999774.49, "order_count": 8, "volume": 9}, {"average": 112442762.37, "date": "2019-12-23", "highest": 124999774.49, "lowest": 63214488.56, "order_count": 5, "volume": 5}, {"average": 122803145.53, "date": "2019-12-24", "highest": 123999420.19, "lowest": 119214280.35, "order_count": 7, "volume": 8}, {"average": 121999083.71, "date": "2019-12-25", "highest": 123998630.56, "lowest": 117999990.0, "order_count": 2, "volume": 3}, {"average": 114999826.79, "date": "2019-12-26", "highest": 114999826.79, "lowest": 114999826.79, "order_count": 1, "volume": 1}, {"average": 116749868.44, "date": "2019-12-27", "highest": 116999789.99, "lowest": 115000000.0, "order_count": 6, "volume": 8}, {"average": 112624999.24, "date": "2019-12-28", "highest": 112999999.0, "lowest": 111499999.94, "order_count": 4, "volume": 4}, {"average": 99155368.52, "date": "2019-12-29", "highest": 111499999.71, "lowest": 63214319.67, "order_count": 8, "volume": 8}, {"average": 109073826.49, "date": "2019-12-30", "highest": 109814319.63, "lowest": 109000000.0, "order_count": 6, "volume": 6}, {"average": 108499999.1, "date": "2019-12-31", "highest": 108999998.82, "lowest": 107999999.0, "order_count": 4, "volume": 6}, {"average": 105930758.25, "date": "2020-01-01", "highest": 107999998.98, "lowest": 91946070.15, "order_count": 7, "volume": 8}, {"average": 103356482.99, "date": "2020-01-02", "highest": 105999999.0, "lowest": 99999855.79, "order_count": 8, "volume": 9}, {"average": 105921878.22, "date": "2020-01-03", "highest": 105999998.9, "lowest": 104999999.0, "order_count": 11, "volume": 15}, {"average": 106742324.79, "date": "2020-01-04", "highest": 106989729.69, "lowest": 106000000.0, "order_count": 4, "volume": 4}, {"average": 106989729.69, "date": "2020-01-05", "highest": 106989729.69, "lowest": 106989729.69, "order_count": 7, "volume": 7}, {"average": 109871134.34, "date": "2020-01-06", "highest": 118499999.99, "lowest": 106994935.89, "order_count": 6, "volume": 8}, {"average": 122870962.83, "date": "2020-01-07", "highest": 124999999.99, "lowest": 100000000.0, "order_count": 9, "volume": 16}, {"average": 123063559.99, "date": "2020-01-08", "highest": 123979999.99, "lowest": 119397800.0, "order_count": 3, "volume": 5}, {"average": 111822241.17, "date": "2020-01-09", "highest": 115999990.0, "lowest": 110000000.0, "order_count": 6, "volume": 9}, {"average": 109999999.39, "date": "2020-01-10", "highest": 109999999.99, "lowest": 109999998.99, "order_count": 7, "volume": 15}, {"average": 108492298.33, "date": "2020-01-11", "highest": 109999997.98, "lowest": 63399900.53, "order_count": 10, "volume": 13}, {"average": 109615382.98, "date": "2020-01-12", "highest": 109999997.97, "lowest": 108999999.0, "order_count": 12, "volume": 13}, {"average": 86699949.91, "date": "2020-01-13", "highest": 109999997.95, "lowest": 63399901.87, "order_count": 2, "volume": 2}, {"average": 116499999.66, "date": "2020-01-14", "highest": 137000000.0, "lowest": 105000000.0, "order_count": 6, "volume": 6}, {"average": 106666665.99, "date": "2020-01-15", "highest": 109999997.97, "lowest": 105000000.0, "order_count": 6, "volume": 9}, {"average": 108499999.49, "date": "2020-01-16", "highest": 109999997.97, "lowest": 108000000.0, "order_count": 3, "volume": 4}, {"average": 117499986.24, "date": "2020-01-17", "highest": 124999999.99, "lowest": 109999999.99, "order_count": 7, "volume": 8}, {"average": 94499967.18, "date": "2020-01-18", "highest": 109999999.99, "lowest": 63499901.57, "order_count": 3, "volume": 3}, {"average": 112999999.77, "date": "2020-01-19", "highest": 137000000.0, "lowest": 109999999.99, "order_count": 9, "volume": 9}, {"average": 119998960.82, "date": "2020-01-20", "highest": 124997920.97, "lowest": 114999999.99, "order_count": 5, "volume": 6}, {"average": 119999101.28, "date": "2020-01-21", "highest": 124997902.99, "lowest": 114999999.99, "order_count": 6, "volume": 7}, {"average": 121873972.1, "date": "2020-01-22", "highest": 124997902.99, "lowest": 118750041.21, "order_count": 4, "volume": 4}, {"average": 86252041.2, "date": "2020-01-23", "highest": 108999989.11, "lowest": 63504093.28, "order_count": 2, "volume": 2}, {"average": 101215708.63, "date": "2020-01-24", "highest": 107499994.5, "lowest": 63509993.39, "order_count": 5, "volume": 7}, {"average": 99252024.94, "date": "2020-01-25", "highest": 107999994.05, "lowest": 63509993.39, "order_count": 8, "volume": 10}, {"average": 109999999.99, "date": "2020-01-26", "highest": 109999999.99, "lowest": 109999999.99, "order_count": 4, "volume": 5}, {"average": 114285106.85, "date": "2020-01-27", "highest": 114998985.0, "lowest": 110000000.0, "order_count": 6, "volume": 7}, {"average": 107249721.94, "date": "2020-01-28", "highest": 114499443.88, "lowest": 100000000.0, "order_count": 3, "volume": 4}, {"average": 114124860.22, "date": "2020-01-29", "highest": 114998888.96, "lowest": 113999999.0, "order_count": 7, "volume": 8}, {"average": 98770911.05, "date": "2020-01-30", "highest": 115000000.0, "lowest": 63599094.35, "order_count": 6, "volume": 7}, {"average": 124997887.98, "date": "2020-01-31", "highest": 124997887.98, "lowest": 124997887.98, "order_count": 1, "volume": 1}, {"average": 109648186.53, "date": "2020-02-01", "highest": 124997880.0, "lowest": 63599106.12, "order_count": 3, "volume": 4}, {"average": 124664896.61, "date": "2020-02-02", "highest": 124997875.0, "lowest": 123000000.0, "order_count": 4, "volume": 6}, {"average": 112856542.42, "date": "2020-02-03", "highest": 124997898.48, "lowest": 110000000.0, "order_count": 7, "volume": 7}, {"average": 124745906.22, "date": "2020-02-04", "highest": 124997874.97, "lowest": 123989999.99, "order_count": 4, "volume": 4}, {"average": 124241980.49, "date": "2020-02-05", "highest": 124997921.98, "lowest": 123989999.99, "order_count": 3, "volume": 4}, {"average": 123516666.64, "date": "2020-02-06", "highest": 123849999.96, "lowest": 122840000.0, "order_count": 6, "volume": 9}, {"average": 124309168.76, "date": "2020-02-07", "highest": 124997921.98, "lowest": 123849999.95, "order_count": 5, "volume": 5}, {"average": 122999996.63, "date": "2020-02-08", "highest": 122999999.94, "lowest": 122999990.0, "order_count": 3, "volume": 6}, {"average": 116568813.31, "date": "2020-02-09", "highest": 122999989.98, "lowest": 65119399.94, "order_count": 8, "volume": 9}, {"average": 122166661.46, "date": "2020-02-10", "highest": 122999989.6, "lowest": 121999999.98, "order_count": 5, "volume": 6}, {"average": 114799999.98, "date": "2020-02-11", "highest": 121999999.96, "lowest": 110000000.0, "order_count": 4, "volume": 5}, {"average": 121249995.85, "date": "2020-02-12", "highest": 121999989.9, "lowest": 120000000.0, "order_count": 6, "volume": 8}, {"average": 121999980.85, "date": "2020-02-13", "highest": 121999989.0, "lowest": 121999977.7, "order_count": 5, "volume": 7}, {"average": 118999982.65, "date": "2020-02-14", "highest": 121999976.87, "lowest": 110000000.0, "order_count": 4, "volume": 4}, {"average": 121999972.67, "date": "2020-02-15", "highest": 121999974.0, "lowest": 121999970.0, "order_count": 2, "volume": 3}, {"average": 121135867.0, "date": "2020-02-18", "highest": 121135867.0, "lowest": 121135867.0, "order_count": 2, "volume": 3}, {"average": 95425370.99, "date": "2020-02-19", "highest": 110565000.0, "lowest": 65146112.98, "order_count": 3, "volume": 3}, {"average": 115000000.0, "date": "2020-02-20", "highest": 115000000.0, "lowest": 115000000.0, "order_count": 1, "volume": 1}, {"average": 107132500.61, "date": "2020-02-21", "highest": 109142180.0, "lowest": 100138072.97, "order_count": 7, "volume": 9}, {"average": 94312917.69, "date": "2020-02-22", "highest": 100142179.95, "lowest": 65166606.41, "order_count": 6, "volume": 6}, {"average": 91073143.51, "date": "2020-02-23", "highest": 98146287.01, "lowest": 85000000.0, "order_count": 3, "volume": 6}, {"average": 90004541.39, "date": "2020-02-24", "highest": 98133906.48, "lowest": 65614113.71, "order_count": 4, "volume": 4}, {"average": 87676163.01, "date": "2020-02-25", "highest": 98123979.18, "lowest": 65614860.34, "order_count": 6, "volume": 7}, {"average": 87315536.5, "date": "2020-02-26", "highest": 89499999.99, "lowest": 86638700.22, "order_count": 7, "volume": 11}, {"average": 87377407.61, "date": "2020-02-27", "highest": 98132223.08, "lowest": 81999999.88, "order_count": 3, "volume": 3}, {"average": 79714285.7, "date": "2020-02-28", "highest": 79999999.98, "lowest": 79000000.0, "order_count": 2, "volume": 7}, {"average": 78461538.45, "date": "2020-02-29", "highest": 79999999.98, "lowest": 75000000.0, "order_count": 9, "volume": 13}, {"average": 88999999.97, "date": "2020-03-01", "highest": 88999999.97, "lowest": 88999999.97, "order_count": 3, "volume": 4}, {"average": 88999999.97, "date": "2020-03-02", "highest": 88999999.97, "lowest": 88999999.97, "order_count": 7, "volume": 7}, {"average": 84999999.96, "date": "2020-03-04", "highest": 85000000.0, "lowest": 84999999.93, "order_count": 5, "volume": 5}, {"average": 92451102.25, "date": "2020-03-05", "highest": 137157716.2, "lowest": 84999999.93, "order_count": 7, "volume": 7}, {"average": 84999999.97, "date": "2020-03-06", "highest": 85000000.0, "lowest": 84999999.93, "order_count": 5, "volume": 6}, {"average": 98132072.6, "date": "2020-03-07", "highest": 98132072.6, "lowest": 98132072.58, "order_count": 10, "volume": 10}, {"average": 97066036.05, "date": "2020-03-09", "highest": 98132072.6, "lowest": 95999999.5, "order_count": 4, "volume": 4}, {"average": 98132072.59, "date": "2020-03-10", "highest": 98132072.59, "lowest": 98132072.59, "order_count": 1, "volume": 1}, {"average": 81983536.3, "date": "2020-03-11", "highest": 98132072.6, "lowest": 65835000.0, "order_count": 5, "volume": 8}, {"average": 98048048.4, "date": "2020-03-12", "highest": 98132072.6, "lowest": 97880000.0, "order_count": 2, "volume": 3}, {"average": 98134024.23, "date": "2020-03-13", "highest": 98140000.0, "lowest": 98131036.34, "order_count": 3, "volume": 3}, {"average": 98140000.0, "date": "2020-03-14", "highest": 98140000.0, "lowest": 98140000.0, "order_count": 4, "volume": 6}, {"average": 96766000.0, "date": "2020-03-15", "highest": 98140000.0, "lowest": 95000000.0, "order_count": 5, "volume": 5}, {"average": 98140000.0, "date": "2020-03-16", "highest": 98140000.0, "lowest": 98140000.0, "order_count": 2, "volume": 3}, {"average": 108920544.98, "date": "2020-03-17", "highest": 119700000.0, "lowest": 98141089.96, "order_count": 3, "volume": 4}, {"average": 119700000.0, "date": "2020-03-18", "highest": 119700000.0, "lowest": 119700000.0, "order_count": 2, "volume": 2}, {"average": 116466666.67, "date": "2020-03-19", "highest": 119700000.0, "lowest": 110000000.0, "order_count": 6, "volume": 6}, {"average": 118900000.0, "date": "2020-03-20", "highest": 118900000.0, "lowest": 118900000.0, "order_count": 4, "volume": 6}, {"average": 118400000.0, "date": "2020-03-21", "highest": 118900000.0, "lowest": 117900000.0, "order_count": 2, "volume": 2}, {"average": 118325000.0, "date": "2020-03-22", "highest": 118700000.0, "lowest": 117950000.0, "order_count": 4, "volume": 4}, {"average": 118700000.0, "date": "2020-03-23", "highest": 118700000.0, "lowest": 118700000.0, "order_count": 4, "volume": 4}, {"average": 118700000.0, "date": "2020-03-24", "highest": 118800000.0, "lowest": 118650000.0, "order_count": 6, "volume": 7}, {"average": 118700000.0, "date": "2020-03-25", "highest": 118700000.0, "lowest": 118700000.0, "order_count": 1, "volume": 1}, {"average": 118700000.0, "date": "2020-03-26", "highest": 118700000.0, "lowest": 118700000.0, "order_count": 6, "volume": 6}, {"average": 118700000.0, "date": "2020-03-27", "highest": 118700000.0, "lowest": 118700000.0, "order_count": 5, "volume": 5}, {"average": 116000000.0, "date": "2020-03-28", "highest": 116900000.0, "lowest": 115550000.0, "order_count": 5, "volume": 6}, {"average": 115100000.0, "date": "2020-03-29", "highest": 115200000.0, "lowest": 114900000.0, "order_count": 3, "volume": 3}, {"average": 114850000.0, "date": "2020-03-30", "highest": 114900000.0, "lowest": 114800000.0, "order_count": 4, "volume": 4}, {"average": 116920000.0, "date": "2020-03-31", "highest": 118300000.0, "lowest": 115150000.0, "order_count": 9, "volume": 10}, {"average": 118400000.0, "date": "2020-04-01", "highest": 118800000.0, "lowest": 118200000.0, "order_count": 3, "volume": 3}, {"average": 117800000.0, "date": "2020-04-02", "highest": 117800000.0, "lowest": 117800000.0, "order_count": 1, "volume": 1}, {"average": 119362373.71, "date": "2020-04-03", "highest": 121050000.0, "lowest": 117900000.0, "order_count": 8, "volume": 8}, {"average": 121100000.0, "date": "2020-04-04", "highest": 121100000.0, "lowest": 121100000.0, "order_count": 1, "volume": 1}, {"average": 121100000.0, "date": "2020-04-05", "highest": 121100000.0, "lowest": 121100000.0, "order_count": 2, "volume": 2}, {"average": 105328750.0, "date": "2020-04-06", "highest": 120650000.0, "lowest": 90010000.0, "order_count": 6, "volume": 8}, {"average": 118019933.5, "date": "2020-04-07", "highest": 121139867.0, "lowest": 114900000.0, "order_count": 2, "volume": 2}, {"average": 105400000.0, "date": "2020-04-08", "highest": 113100000.0, "lowest": 90000000.0, "order_count": 3, "volume": 3}, {"average": 111925000.0, "date": "2020-04-09", "highest": 112000000.0, "lowest": 111900000.0, "order_count": 4, "volume": 4}, {"average": 101628800.0, "date": "2020-04-10", "highest": 114400000.0, "lowest": 89990000.0, "order_count": 12, "volume": 25}, {"average": 95506666.67, "date": "2020-04-11", "highest": 109900000.0, "lowest": 81000000.0, "order_count": 6, "volume": 12}, {"average": 93526666.67, "date": "2020-04-12", "highest": 99890000.0, "lowest": 80790000.0, "order_count": 6, "volume": 6}, {"average": 94894000.0, "date": "2020-04-13", "highest": 94910000.0, "lowest": 94880000.0, "order_count": 5, "volume": 5}, {"average": 94790000.0, "date": "2020-04-14", "highest": 94790000.0, "lowest": 94790000.0, "order_count": 4, "volume": 4}, {"average": 93096666.67, "date": "2020-04-15", "highest": 94645000.0, "lowest": 90000000.0, "order_count": 3, "volume": 3}, {"average": 94895000.0, "date": "2020-04-16", "highest": 95000000.0, "lowest": 94790000.0, "order_count": 4, "volume": 4}, {"average": 107200000.0, "date": "2020-04-17", "highest": 109900000.0, "lowest": 103150000.0, "order_count": 7, "volume": 10}, {"average": 106200000.0, "date": "2020-04-18", "highest": 110000000.0, "lowest": 103900000.0, "order_count": 12, "volume": 13}, {"average": 94428000.0, "date": "2020-04-19", "highest": 103900000.0, "lowest": 80220000.0, "order_count": 4, "volume": 5}, {"average": 91666666.67, "date": "2020-04-20", "highest": 97395000.0, "lowest": 80210000.0, "order_count": 3, "volume": 3}]