[{"average": 15.0, "date": "2019-07-16", "highest": 15.0, "lowest": 15.0, "order_count": 1, "volume": 7900}, {"average": 15.0, "date": "2019-09-07", "highest": 15.0, "lowest": 15.0, "order_count": 1, "volume": 66}, {"average": 0.01, "date": "2019-09-17", "highest": 0.01, "lowest": 0.01, "order_count": 1, "volume": 92}, {"average": 0.01, "date": "2019-10-19", "highest": 0.01, "lowest": 0.01, "order_count": 1, "volume": 76}, {"average": 0.01, "date": "2019-10-31", "highest": 0.01, "lowest": 0.01, "order_count": 1, "volume": 50}, {"average": 0.01, "date": "2019-11-17", "highest": 0.01, "lowest": 0.01, "order_count": 1, "volume": 378}]