[{"average": 16444435.99, "date": "2019-03-05", "highest": 16444435.99, "lowest": 16444435.99, "order_count": 1, "volume": 1}, {"average": 16750751.8, "date": "2019-03-17", "highest": 17975999.0, "lowest": 16444440.0, "order_count": 4, "volume": 5}, {"average": 30649999.99, "date": "2019-03-24", "highest": 30649999.99, "lowest": 30649999.99, "order_count": 1, "volume": 1}, {"average": 30600000.0, "date": "2019-03-26", "highest": 30600000.0, "lowest": 30600000.0, "order_count": 1, "volume": 1}, {"average": 22000000.0, "date": "2019-04-09", "highest": 22000000.0, "lowest": 22000000.0, "order_count": 1, "volume": 1}, {"average": 30650000.0, "date": "2019-04-11", "highest": 30650000.0, "lowest": 30650000.0, "order_count": 3, "volume": 3}, {"average": 28487500.0, "date": "2019-04-12", "highest": 28487500.0, "lowest": 28487500.0, "order_count": 1, "volume": 1}, {"average": 30000000.0, "date": "2019-04-13", "highest": 30000000.0, "lowest": 30000000.0, "order_count": 1, "volume": 1}, {"average": 34199999.99, "date": "2019-04-14", "highest": 34199999.99, "lowest": 34199999.99, "order_count": 1, "volume": 2}, {"average": 42999999.99, "date": "2019-04-15", "highest": 42999999.99, "lowest": 42999999.99, "order_count": 1, "volume": 1}, {"average": 42999999.99, "date": "2019-04-16", "highest": 42999999.99, "lowest": 42999999.99, "order_count": 1, "volume": 1}, {"average": 42999999.99, "date": "2019-04-18", "highest": 42999999.99, "lowest": 42999999.99, "order_count": 1, "volume": 2}, {"average": 42999999.99, "date": "2019-04-19", "highest": 42999999.99, "lowest": 42999999.99, "order_count": 1, "volume": 2}, {"average": 39999984.85, "date": "2019-04-22", "highest": 39999984.85, "lowest": 39999984.85, "order_count": 1, "volume": 1}, {"average": 23999998.03, "date": "2019-05-09", "highest": 23999998.03, "lowest": 23999998.03, "order_count": 1, "volume": 1}, {"average": 23999991.35, "date": "2019-05-13", "highest": 23999991.35, "lowest": 23999991.35, "order_count": 1, "volume": 1}, {"average": 23999921.18, "date": "2019-05-28", "highest": 23999921.18, "lowest": 23999921.18, "order_count": 1, "volume": 1}, {"average": 8500980.0, "date": "2019-05-29", "highest": 8500980.0, "lowest": 8500980.0, "order_count": 1, "volume": 1}, {"average": 23999921.08, "date": "2019-05-31", "highest": 23999921.08, "lowest": 23999921.08, "order_count": 1, "volume": 1}, {"average": 23999921.09, "date": "2019-06-02", "highest": 23999921.09, "lowest": 23999921.09, "order_count": 1, "volume": 1}, {"average": 23999923.39, "date": "2019-06-03", "highest": 23999923.39, "lowest": 23999923.39, "order_count": 1, "volume": 1}, {"average": 23999923.39, "date": "2019-06-05", "highest": 23999923.39, "lowest": 23999923.39, "order_count": 1, "volume": 1}, {"average": 23999923.39, "date": "2019-06-07", "highest": 23999923.39, "lowest": 23999923.39, "order_count": 1, "volume": 1}, {"average": 23999923.39, "date": "2019-06-09", "highest": 23999923.39, "lowest": 23999923.39, "order_count": 1, "volume": 1}, {"average": 8500980.0, "date": "2019-07-01", "highest": 8500980.0, "lowest": 8500980.0, "order_count": 1, "volume": 1}, {"average": 21214458.38, "date": "2019-07-07", "highest": 21214458.38, "lowest": 21214458.38, "order_count": 1, "volume": 1}, {"average": 20499976.62, "date": "2019-07-11", "highest": 20499976.62, "lowest": 20499976.62, "order_count": 1, "volume": 1}, {"average": 20499979.29, "date": "2019-07-13", "highest": 20499979.29, "lowest": 20499979.29, "order_count": 1, "volume": 1}, {"average": 19999998.99, "date": "2019-08-20", "highest": 19999998.99, "lowest": 19999998.99, "order_count": 1, "volume": 1}, {"average": 15000000.0, "date": "2019-09-27", "highest": 15000000.0, "lowest": 15000000.0, "order_count": 1, "volume": 1}, {"average": 17124999.63, "date": "2019-10-11", "highest": 17500000.0, "lowest": 16999999.8, "order_count": 3, "volume": 8}, {"average": 15999999.0, "date": "2019-10-12", "highest": 15999999.0, "lowest": 15999999.0, "order_count": 1, "volume": 1}, {"average": 16374999.54, "date": "2019-10-13", "highest": 17124999.63, "lowest": 15999999.5, "order_count": 3, "volume": 3}, {"average": 19999999.0, "date": "2019-10-21", "highest": 19999999.0, "lowest": 19999999.0, "order_count": 1, "volume": 1}, {"average": 19890000.0, "date": "2019-10-31", "highest": 19890000.0, "lowest": 19890000.0, "order_count": 1, "volume": 1}, {"average": 59999999.0, "date": "2019-12-09", "highest": 59999999.0, "lowest": 59999999.0, "order_count": 1, "volume": 1}, {"average": 55999999.0, "date": "2019-12-13", "highest": 55999999.0, "lowest": 55999999.0, "order_count": 1, "volume": 1}, {"average": 45000000.0, "date": "2019-12-29", "highest": 45000000.0, "lowest": 45000000.0, "order_count": 1, "volume": 1}, {"average": 1.0, "date": "2020-01-13", "highest": 1.0, "lowest": 1.0, "order_count": 1, "volume": 5}, {"average": 43999999.98, "date": "2020-01-27", "highest": 43999999.98, "lowest": 43999999.98, "order_count": 1, "volume": 1}, {"average": 39989989.0, "date": "2020-02-12", "highest": 39989989.0, "lowest": 39989989.0, "order_count": 1, "volume": 1}, {"average": 36988986.0, "date": "2020-03-11", "highest": 36988986.0, "lowest": 36988986.0, "order_count": 1, "volume": 1}, {"average": 30000000.0, "date": "2020-03-25", "highest": 30000000.0, "lowest": 30000000.0, "order_count": 1, "volume": 1}, {"average": 31970000.0, "date": "2020-03-26", "highest": 31970000.0, "lowest": 31970000.0, "order_count": 1, "volume": 1}, {"average": 29992500.0, "date": "2020-04-04", "highest": 30000000.0, "lowest": 29990000.0, "order_count": 4, "volume": 4}, {"average": 31790000.0, "date": "2020-04-07", "highest": 31790000.0, "lowest": 31790000.0, "order_count": 1, "volume": 1}, {"average": 30350000.0, "date": "2020-04-15", "highest": 30350000.0, "lowest": 30350000.0, "order_count": 1, "volume": 1}]